django_chunk_upload_handlers/__init__.py
django_chunk_upload_handlers/apps.py
django_chunk_upload_handlers/clam_av.py
django_chunk_upload_handlers/models.py
django_chunk_upload_handlers/s3.py
django_chunk_upload_handlers/util.py
django_chunk_upload_handlers/migrations/0001_initial.py
django_chunk_upload_handlers/migrations/0002_alter_scannedfile_id.py
django_chunk_upload_handlers/migrations/__init__.py
django_chunk_upload_handlers/test/__init__.py
django_chunk_upload_handlers/test/test_clam_av.py
django_chunk_upload_handlers/test/test_s3.py
django_chunk_upload_handlers-0.0.15.dist-info/LICENSE
django_chunk_upload_handlers-0.0.15.dist-info/METADATA
django_chunk_upload_handlers-0.0.15.dist-info/WHEEL
django_chunk_upload_handlers-0.0.15.dist-info/top_level.txt
django_chunk_upload_handlers-0.0.15.dist-info/RECORD
