Metadata-Version: 2.1
Name: django_chunk_upload_handlers
Version: 0.0.15
Summary: Chunking Django file handlers for S3 and ClamAV service uploads
Home-page: https://github.com/uktrade/django-chunk-s3-av-upload-handlers
Author: Ross Miller
Author-email: ross.miller@digital.trade.gov.uk
Classifier: Programming Language :: Python :: 3
Classifier: License :: OSI Approved :: MIT License
Classifier: Operating System :: OS Independent
Requires-Python: >=3.8
License-File: LICENSE
Requires-Dist: django <6.0,>=4.2
Requires-Dist: boto3 >=1.17.89
Requires-Dist: django-storages >=1.11.1
